tests/__init__.py
tests/test_export.py
zarr_tools/__init__.py
zarr_tools/__main__.py
zarr_tools/_version.py
zarr_tools/convert.py
zarr_tools-0.6.0.dist-info/licenses/LICENSE
zarr_tools-0.6.0.dist-info/METADATA
zarr_tools-0.6.0.dist-info/WHEEL
zarr_tools-0.6.0.dist-info/top_level.txt
zarr_tools-0.6.0.dist-info/RECORD
