Metadata-Version: 2.4
Name: zarr_tools
Version: 0.6.0
Summary: Convert nd2 to zarr
Home-page: https://github.com/BaroudLab/zarr-tools
Author: Andrey Aristov
Author-email: aaristov@pasteur.fr
License: BSD-3-Clause
Project-URL: Bug Tracker, https://gitlab.pasteur.fr/aaristov/zarr-tools/issues
Classifier: Development Status :: 2 - Pre-Alpha
Classifier: Intended Audience :: Developers
Classifier: Operating System :: OS Independent
Classifier: Programming Language :: Python
Classifier: Programming Language :: Python :: 3
Classifier: Programming Language :: Python :: 3 :: Only
Classifier: Programming Language :: Python :: Implementation :: CPython
Classifier: Topic :: Software Development :: Testing
Requires-Python: >=3.11
License-File: LICENSE
Requires-Dist: dask
Requires-Dist: fire
Requires-Dist: nd2
Requires-Dist: zarr>=3.0
Dynamic: license-file
